ysfutils/__init__.py
ysfutils/config.py
ysfutils/dataframe.py
ysfutils/dingding.py
ysfutils/error.py
ysfutils/github.py
ysfutils/job.py
ysfutils/list.py
ysfutils/mongo.py
ysfutils/pid.py
ysfutils/sqlites.py
ysfutils/ths.js
ysfutils/ths.py
ysfutils-1.0.19.dist-info/LICENSE
ysfutils-1.0.19.dist-info/METADATA
ysfutils-1.0.19.dist-info/WHEEL
ysfutils-1.0.19.dist-info/top_level.txt
ysfutils-1.0.19.dist-info/RECORD
