Metadata-Version: 2.1
Name: ysfutils
Version: 1.0.19
Summary: My library of frequently used tools.
Home-page: https://github.com/yingsf/ysfutils-1.0.19
Download-URL: https://github.com/yingsf/ysfutils-1.0.19/tarball/master
Author: ShuFeng Ying
Author-email: me@yingsf.com
Maintainer: ShuFeng Ying
Maintainer-email: me@yingsf.com
License: MIT
Platform: MacOS
Platform: Unix
Classifier: Development Status :: 4 - Beta
Classifier: Intended Audience :: Developers
Classifier: License :: OSI Approved :: MIT License
Classifier: Natural Language :: English
Classifier: Natural Language :: Chinese (Simplified)
Classifier: Operating System :: MacOS
Classifier: Operating System :: Unix
Classifier: Programming Language :: Python :: 3 :: Only
Requires-Python: >=3.11
License-File: LICENSE
Requires-Dist: APScheduler >=3.10.0
Requires-Dist: Cython >=3.0.0
Requires-Dist: loguru >=0.7.0
Requires-Dist: py-mini-racer >=0.6.0
Requires-Dist: pymongo >=4.7.0
Requires-Dist: pysqlcipher3 >=1.2.0
Requires-Dist: python-box >=7.1.0
Requires-Dist: requests >=2.30.0
